setup.py
circle_area/__init__.py
circle_area/circle.py
circle_area.egg-info/PKG-INFO
circle_area.egg-info/SOURCES.txt
circle_area.egg-info/dependency_links.txt
circle_area.egg-info/top_level.txt