Metadata-Version: 2.1
Name: circle-area
Version: 0.1.0
Summary: A package to compute the area of a circle
Home-page: UNKNOWN
Author: James-Wachuka
Author-email: jewachu26@email.com
License: UNKNOWN
Platform: UNKNOWN
